terraform_drift_detector/__init__.py
terraform_drift_detector/cli.py
terraform_drift_detector/detector.py
terraform_drift_detector-0.1.0.dist-info/licenses/LICENSE
tests/__init__.py
tests/test_basic.py
terraform_drift_detector-0.1.0.dist-info/METADATA
terraform_drift_detector-0.1.0.dist-info/WHEEL
terraform_drift_detector-0.1.0.dist-info/entry_points.txt
terraform_drift_detector-0.1.0.dist-info/top_level.txt
terraform_drift_detector-0.1.0.dist-info/RECORD
